Metadata-Version: 1.1
Name: rpi-ip-bot-client
Version: 1.0
Summary: Command line tool to manage the client part of rpi_ip_bot service.
Home-page: https://github.com/eugene-babichenko/rpi_ip_bot_client
Author: Yevhenii Babichenko
Author-email: eugene.babichenko@gmail.com
License: MIT
Keywords: ip telegram bot raspberry pi
Platform: UNKNOWN
Classifier: Topic :: Utilities
